<?xml version="1.0" encoding="utf-8"?>
<resources>

    <style name="AppTheme" parent="MyBase.Theme">
    </style>

    <style name="MyBase.Theme" parent="Theme.AppCompat.NoActionBar">
        <item name="colorPrimary">@color/primaryColor</item>
        <item name="colorPrimaryDark">@color/primaryColorDark</item>
        <item name="android:textColorPrimary">@color/textColorPrimary</item>
        <item name="colorAccent">@color/accentColor</item>
        <item name="windowNoTitle">true</item>
        <item name="windowActionBar">false</item>
        <item name="android:colorBackground">@color/windowBackground</item>
    </style>

</resources>